[
  {
    "name": "Test Workflow",
    "description": "Test",
    "trigger": {
      "id": "trigger_123",
      "type": "webhook",
      "config": {
        "url": "",
        "method": "POST"
      }
    },
    "actions": [],
    "isActive": true,
    "id": "wf_1768067885943_dmxik9xh3",
    "createdAt": "2026-01-10T17:58:05.943Z",
    "updatedAt": "2026-01-10T17:58:05.943Z"
  },
  {
    "name": "Quick Test",
    "description": "Quick test workflow",
    "trigger": {
      "id": "trigger_test",
      "type": "webhook",
      "config": {
        "url": "",
        "method": "POST"
      }
    },
    "actions": [],
    "isActive": true,
    "id": "wf_1768068055262_wxc3m38x9",
    "createdAt": "2026-01-10T18:00:55.262Z",
    "updatedAt": "2026-01-10T18:00:55.262Z"
  },
  {
    "name": "Workflow 1768068194016",
    "description": "",
    "trigger": {
      "type": "webhook",
      "config": {
        "url": ""
      }
    },
    "actions": [
      {
        "id": "action_1768068181695_lryix0qzo",
        "type": "email",
        "config": {
          "to": "igoraor79@gmail.com",
          "subject": "fdf",
          "body": "fff\n"
        },
        "position": {
          "x": 100,
          "y": 100
        }
      }
    ],
    "isActive": true,
    "id": "wf_1768068194023_5ujvosd6e",
    "createdAt": "2026-01-10T18:03:14.023Z",
    "updatedAt": "2026-01-10T18:03:14.023Z"
  },
  {
    "name": "Workflow 1768068271167",
    "description": "",
    "trigger": {
      "type": "webhook",
      "config": {
        "url": ""
      }
    },
    "actions": [
      {
        "id": "action_1768068260976_p4tzrezxx",
        "type": "email",
        "config": {
          "to": "igoraor79@gmail.com",
          "subject": "афыа",
          "body": "фыафы"
        },
        "position": {
          "x": 100,
          "y": 100
        }
      }
    ],
    "isActive": true,
    "id": "wf_1768068271218_8j9jc4vfc",
    "createdAt": "2026-01-10T18:04:31.218Z",
    "updatedAt": "2026-01-10T18:04:31.218Z"
  },
  {
    "name": "Workflow 1768068426951",
    "description": "",
    "trigger": {
      "type": "webhook",
      "config": {
        "url": ""
      }
    },
    "actions": [
      {
        "id": "action_1768068415816_yvwuebi2w",
        "type": "email",
        "config": {
          "to": "igoraor79@gmail.com",
          "subject": "13213",
          "body": "333"
        },
        "position": {
          "x": 100,
          "y": 100
        }
      }
    ],
    "isActive": true,
    "id": "wf_1768068427381_txwhkjhrm",
    "createdAt": "2026-01-10T18:07:07.381Z",
    "updatedAt": "2026-01-10T18:07:07.381Z"
  },
  {
    "name": "Workflow 1768068510183",
    "description": "",
    "trigger": {
      "type": "webhook",
      "config": {
        "url": ""
      }
    },
    "actions": [
      {
        "id": "action_1768068497496_v9lae1r9m",
        "type": "email",
        "config": {
          "to": "samptv59@gmail.com",
          "subject": "asfsa",
          "body": "fasfas"
        },
        "position": {
          "x": 100,
          "y": 100
        }
      }
    ],
    "isActive": true,
    "id": "wf_1768068510192_zpm8nyviw",
    "createdAt": "2026-01-10T18:08:30.192Z",
    "updatedAt": "2026-01-10T18:08:30.192Z"
  },
  {
    "name": "Test",
    "description": "",
    "trigger": {
      "id": "test",
      "type": "webhook",
      "config": {
        "url": "",
        "method": "POST"
      }
    },
    "actions": [
      {
        "id": "test",
        "type": "email",
        "config": {
          "to": "test@test.com",
          "subject": "Test",
          "body": "Test"
        }
      }
    ],
    "isActive": true,
    "id": "wf_1768068562978_6i4o0mmkn",
    "createdAt": "2026-01-10T18:09:22.978Z",
    "updatedAt": "2026-01-10T18:09:22.978Z"
  },
  {
    "name": "Workflow 1768068636039",
    "description": "",
    "trigger": {
      "type": "webhook",
      "config": {
        "url": ""
      }
    },
    "actions": [
      {
        "id": "action_1768068619743_m87yjclu7",
        "type": "telegram",
        "config": {
          "chatId": "",
          "message": ""
        },
        "position": {
          "x": 100,
          "y": 100
        }
      },
      {
        "id": "action_1768068614791_eni8xla20",
        "type": "email",
        "config": {
          "to": "",
          "subject": "",
          "body": ""
        },
        "position": {
          "x": 100,
          "y": 100
        }
      }
    ],
    "isActive": true,
    "id": "wf_1768068636046_7w7w1a1ly",
    "createdAt": "2026-01-10T18:10:36.046Z",
    "updatedAt": "2026-01-10T18:10:36.046Z"
  },
  {
    "name": "Test",
    "trigger": {
      "type": "webhook",
      "config": {}
    },
    "actions": [
      {
        "type": "email",
        "config": {
          "to": "test@test.com",
          "subject": "Test",
          "body": "Hello"
        }
      }
    ],
    "isActive": true,
    "id": "wf_1768068708009_q0i591k7a",
    "createdAt": "2026-01-10T18:11:48.009Z",
    "updatedAt": "2026-01-10T18:11:48.009Z"
  },
  {
    "name": "Workflow 1768068762247",
    "description": "",
    "trigger": {
      "type": "webhook",
      "config": {
        "url": ""
      }
    },
    "actions": [
      {
        "id": "action_1768068727007_oqi5avuna",
        "type": "email",
        "config": {
          "to": "samptv59@gmail.com",
          "subject": "13213",
          "body": "123123"
        },
        "position": {
          "x": 100,
          "y": 100
        }
      },
      {
        "id": "action_1768068746423_zmlqwj1sv",
        "type": "telegram",
        "config": {
          "chatId": "1003520125389",
          "message": "fdsfds"
        },
        "position": {
          "x": 100,
          "y": 100
        }
      }
    ],
    "isActive": true,
    "id": "wf_1768068762256_nqrn9prtd",
    "createdAt": "2026-01-10T18:12:42.256Z",
    "updatedAt": "2026-01-10T18:12:42.256Z"
  },
  {
    "name": "Workflow 1768068959502",
    "description": "",
    "trigger": {
      "type": "webhook",
      "config": {
        "url": ""
      }
    },
    "actions": [
      {
        "id": "action_1768068944935_lefzfk58f",
        "type": "email",
        "config": {
          "to": "samptv59@gmail.com",
          "subject": "asdad",
          "body": "awdawd"
        },
        "position": {
          "x": 100,
          "y": 100
        }
      },
      {
        "id": "action_1768068945975_8uotmzpqm",
        "type": "telegram",
        "config": {
          "chatId": "1003520125389",
          "message": "dawdaw"
        },
        "position": {
          "x": 100,
          "y": 100
        }
      }
    ],
    "isActive": true,
    "id": "wf_1768068959549_0u7tpow73",
    "createdAt": "2026-01-10T18:15:59.549Z",
    "updatedAt": "2026-01-10T18:15:59.549Z"
  },
  {
    "name": "Workflow 1768069140694",
    "description": "",
    "trigger": {
      "type": "webhook",
      "config": {
        "url": ""
      }
    },
    "actions": [
      {
        "id": "action_1768069126991_kkw5miwwq",
        "type": "email",
        "config": {
          "to": "samptv59@gmail.com",
          "subject": "asdad",
          "body": "asdasd"
        },
        "position": {
          "x": 100,
          "y": 100
        }
      },
      {
        "id": "action_1768069127910_upzvyk1o7",
        "type": "telegram",
        "config": {
          "chatId": "1003520125389",
          "message": "dsfsfd"
        },
        "position": {
          "x": 100,
          "y": 100
        }
      }
    ],
    "isActive": true,
    "id": "wf_1768069140723_4fj3uyjbg",
    "createdAt": "2026-01-10T18:19:00.723Z",
    "updatedAt": "2026-01-10T18:19:00.723Z"
  },
  {
    "name": "Workflow 1768069233254",
    "description": "",
    "trigger": {
      "type": "webhook",
      "config": {
        "url": ""
      }
    },
    "actions": [
      {
        "id": "action_1768069221870_q6uncp2rb",
        "type": "email",
        "config": {
          "to": "igoraor79@gmail.com",
          "subject": "fds",
          "body": "fsdfsdf"
        },
        "position": {
          "x": 100,
          "y": 100
        }
      }
    ],
    "isActive": true,
    "id": "wf_1768069233280_4exylr9g8",
    "createdAt": "2026-01-10T18:20:33.280Z",
    "updatedAt": "2026-01-10T18:20:33.280Z"
  },
  {
    "name": "Workflow 1768069303494",
    "description": "",
    "trigger": {
      "type": "webhook",
      "config": {
        "url": ""
      }
    },
    "actions": [
      {
        "id": "action_1768069289158_ih6anqusf",
        "type": "email",
        "config": {
          "to": "samptv59@gmail.com",
          "subject": "3123",
          "body": "12313"
        },
        "position": {
          "x": 100,
          "y": 100
        }
      }
    ],
    "isActive": true,
    "id": "wf_1768069303523_2ms675t06",
    "createdAt": "2026-01-10T18:21:43.523Z",
    "updatedAt": "2026-01-10T18:21:43.523Z"
  },
  {
    "name": "Workflow 1768069344590",
    "description": "",
    "trigger": {
      "type": "webhook",
      "config": {
        "url": ""
      }
    },
    "actions": [
      {
        "id": "action_1768069333870_isina8ycf",
        "type": "telegram",
        "config": {
          "chatId": "1003520125389",
          "message": "sdfsf"
        },
        "position": {
          "x": 100,
          "y": 100
        }
      }
    ],
    "isActive": true,
    "id": "wf_1768069344596_c693oem4l",
    "createdAt": "2026-01-10T18:22:24.596Z",
    "updatedAt": "2026-01-10T18:22:24.596Z"
  },
  {
    "name": "Workflow 1768069376510",
    "description": "",
    "trigger": {
      "type": "webhook",
      "config": {
        "url": ""
      }
    },
    "actions": [
      {
        "id": "action_1768069366678_s7nfdhheh",
        "type": "telegram",
        "config": {
          "chatId": "1003520125389",
          "message": "1003520125389"
        },
        "position": {
          "x": 100,
          "y": 100
        }
      }
    ],
    "isActive": true,
    "id": "wf_1768069376513_0948mkat2",
    "createdAt": "2026-01-10T18:22:56.513Z",
    "updatedAt": "2026-01-10T18:22:56.513Z"
  },
  {
    "name": "Workflow 1768069411414",
    "description": "",
    "trigger": {
      "type": "webhook",
      "config": {
        "url": ""
      }
    },
    "actions": [
      {
        "id": "action_1768069389574_f6gm69pz9",
        "type": "email",
        "config": {
          "to": "samptv59@gmail.com",
          "subject": "dasd",
          "body": "asdas"
        },
        "position": {
          "x": 100,
          "y": 100
        }
      },
      {
        "id": "action_1768069393126_0bgrt2y0f",
        "type": "telegram",
        "config": {
          "chatId": "1003520125389",
          "message": "1003520125389"
        },
        "position": {
          "x": 100,
          "y": 100
        }
      }
    ],
    "isActive": true,
    "id": "wf_1768069411418_jekav7b5z",
    "createdAt": "2026-01-10T18:23:31.418Z",
    "updatedAt": "2026-01-10T18:23:31.418Z"
  },
  {
    "name": "Workflow 1768069511030",
    "description": "",
    "trigger": {
      "type": "webhook",
      "config": {
        "url": ""
      }
    },
    "actions": [
      {
        "id": "action_1768069498062_cxctyqr6z",
        "type": "email",
        "config": {
          "to": "samptv59@gmail.com",
          "subject": "asdas",
          "body": "asdsad"
        },
        "position": {
          "x": 100,
          "y": 100
        }
      },
      {
        "id": "action_1768069498718_yze2075xl",
        "type": "telegram",
        "config": {
          "chatId": "1003520125389",
          "message": "1003520125389"
        },
        "position": {
          "x": 100,
          "y": 100
        }
      }
    ],
    "isActive": true,
    "id": "wf_1768069511058_7bjtrrh5h",
    "createdAt": "2026-01-10T18:25:11.058Z",
    "updatedAt": "2026-01-10T18:25:11.058Z"
  },
  {
    "name": "Test",
    "trigger": {
      "type": "webhook",
      "config": {}
    },
    "actions": [
      {
        "type": "email",
        "config": {
          "to": "test@test.com",
          "subject": "Test",
          "body": "Hello"
        }
      }
    ],
    "isActive": true,
    "id": "wf_1768069547949_tiintnso5",
    "createdAt": "2026-01-10T18:25:47.949Z",
    "updatedAt": "2026-01-10T18:25:47.949Z"
  },
  {
    "name": "Test",
    "trigger": {
      "type": "webhook",
      "config": {}
    },
    "actions": [
      {
        "type": "email",
        "config": {
          "to": "test@test.com",
          "subject": "Test",
          "body": "Hello"
        }
      }
    ],
    "isActive": true,
    "id": "wf_1768069560558_enj1mgbfm",
    "createdAt": "2026-01-10T18:26:00.558Z",
    "updatedAt": "2026-01-10T18:26:00.558Z"
  },
  {
    "name": "Test",
    "trigger": {
      "type": "webhook",
      "config": {}
    },
    "actions": [
      {
        "type": "email",
        "config": {
          "to": "samptv59@gmail.com",
          "subject": "Test",
          "body": "Hello"
        }
      }
    ],
    "isActive": true,
    "id": "wf_1768069584949_qtddgt2lm",
    "createdAt": "2026-01-10T18:26:24.949Z",
    "updatedAt": "2026-01-10T18:26:24.950Z"
  },
  {
    "name": "Workflow 1768069634470",
    "description": "",
    "trigger": {
      "type": "webhook",
      "config": {
        "url": ""
      }
    },
    "actions": [
      {
        "id": "action_1768069612982_qdg83m15d",
        "type": "email",
        "config": {
          "to": "samptv59@gmail.com",
          "subject": "312313",
          "body": "12313"
        },
        "position": {
          "x": 100,
          "y": 100
        }
      },
      {
        "id": "action_1768069613725_ci56ndpvl",
        "type": "telegram",
        "config": {
          "chatId": "1003520125389",
          "message": "1003520125389"
        },
        "position": {
          "x": 100,
          "y": 100
        }
      }
    ],
    "isActive": true,
    "id": "wf_1768069634477_tuc3mjn5j",
    "createdAt": "2026-01-10T18:27:14.477Z",
    "updatedAt": "2026-01-10T18:27:14.477Z"
  },
  {
    "name": "Test",
    "trigger": {
      "type": "webhook",
      "config": {}
    },
    "actions": [
      {
        "type": "telegram",
        "config": {
          "message": "Test message"
        }
      }
    ],
    "isActive": true,
    "id": "wf_1768069708056_gibcpuykr",
    "createdAt": "2026-01-10T18:28:28.056Z",
    "updatedAt": "2026-01-10T18:28:28.056Z"
  },
  {
    "name": "Test",
    "trigger": {
      "type": "webhook",
      "config": {}
    },
    "actions": [
      {
        "type": "email",
        "config": {
          "to": "samptv59@gmail.com",
          "subject": "Test",
          "body": "Hello"
        }
      },
      {
        "type": "telegram",
        "config": {
          "message": "Test telegram"
        }
      }
    ],
    "isActive": true,
    "id": "wf_1768069713721_uaffs90iu",
    "createdAt": "2026-01-10T18:28:33.721Z",
    "updatedAt": "2026-01-10T18:28:33.721Z"
  },
  {
    "name": "Test",
    "trigger": {
      "type": "webhook",
      "config": {}
    },
    "actions": [
      {
        "type": "email",
        "config": {
          "to": "samptv59@gmail.com",
          "subject": "Test",
          "body": "Hello"
        }
      }
    ],
    "isActive": true,
    "id": "wf_1768069892174_q1dtpiylu",
    "createdAt": "2026-01-10T18:31:32.174Z",
    "updatedAt": "2026-01-10T18:31:32.174Z"
  },
  {
    "name": "Test Run Workflow",
    "trigger": {
      "type": "webhook",
      "config": {}
    },
    "actions": [
      {
        "type": "email",
        "config": {
          "to": "samptv59@gmail.com",
          "subject": "API Run Test",
          "body": "Hello from API run!"
        }
      }
    ],
    "id": "wf_1768070558310_4jxjznsj8",
    "createdAt": "2026-01-10T18:42:38.310Z",
    "updatedAt": "2026-01-10T18:42:38.310Z"
  },
  {
    "name": "Workflow 1768156580662",
    "description": "",
    "trigger": {
      "type": "webhook",
      "config": {
        "url": ""
      }
    },
    "actions": [
      {
        "id": "action_1",
        "type": "email",
        "config": {
          "to": "samptv59@gmail.com",
          "subject": "adwda",
          "body": "ddd",
          "from": ""
        },
        "position": {
          "x": 100,
          "y": 100
        }
      }
    ],
    "isActive": true,
    "id": "wf_1768156581095_bw397nzy1",
    "createdAt": "2026-01-11T18:36:21.095Z",
    "updatedAt": "2026-01-11T18:36:21.095Z"
  },
  {
    "name": "Workflow 1768156580691",
    "description": "",
    "trigger": {
      "type": "webhook",
      "config": {
        "url": ""
      }
    },
    "actions": [
      {
        "id": "action_1",
        "type": "email",
        "config": {
          "to": "samptv59@gmail.com",
          "subject": "adwda",
          "body": "ddd",
          "from": ""
        },
        "position": {
          "x": 100,
          "y": 100
        }
      }
    ],
    "isActive": true,
    "id": "wf_1768156581116_ovl3o7a03",
    "createdAt": "2026-01-11T18:36:21.116Z",
    "updatedAt": "2026-01-11T18:36:21.116Z"
  },
  {
    "name": "Workflow 1768156585369",
    "description": "",
    "trigger": {
      "type": "webhook",
      "config": {
        "url": ""
      }
    },
    "actions": [
      {
        "id": "action_1",
        "type": "email",
        "config": {
          "to": "samptv59@gmail.com",
          "subject": "adwda",
          "body": "ddd",
          "from": ""
        },
        "position": {
          "x": 100,
          "y": 100
        }
      }
    ],
    "isActive": true,
    "id": "wf_1768156585376_i3jz9d79d",
    "createdAt": "2026-01-11T18:36:25.376Z",
    "updatedAt": "2026-01-11T18:36:25.376Z"
  },
  {
    "name": "Workflow 1768156585396",
    "description": "",
    "trigger": {
      "type": "webhook",
      "config": {
        "url": ""
      }
    },
    "actions": [
      {
        "id": "action_1",
        "type": "email",
        "config": {
          "to": "samptv59@gmail.com",
          "subject": "adwda",
          "body": "ddd",
          "from": ""
        },
        "position": {
          "x": 100,
          "y": 100
        }
      }
    ],
    "isActive": true,
    "id": "wf_1768156585410_d6noeafvd",
    "createdAt": "2026-01-11T18:36:25.410Z",
    "updatedAt": "2026-01-11T18:36:25.410Z"
  },
  {
    "name": "Workflow 1768156586575",
    "description": "",
    "trigger": {
      "type": "webhook",
      "config": {
        "url": ""
      }
    },
    "actions": [
      {
        "id": "action_1",
        "type": "email",
        "config": {
          "to": "samptv59@gmail.com",
          "subject": "adwda",
          "body": "ddd",
          "from": ""
        },
        "position": {
          "x": 100,
          "y": 100
        }
      }
    ],
    "isActive": true,
    "id": "wf_1768156586582_67e07vhxg",
    "createdAt": "2026-01-11T18:36:26.582Z",
    "updatedAt": "2026-01-11T18:36:26.582Z"
  },
  {
    "name": "Workflow 1768156586600",
    "description": "",
    "trigger": {
      "type": "webhook",
      "config": {
        "url": ""
      }
    },
    "actions": [
      {
        "id": "action_1",
        "type": "email",
        "config": {
          "to": "samptv59@gmail.com",
          "subject": "adwda",
          "body": "ddd",
          "from": ""
        },
        "position": {
          "x": 100,
          "y": 100
        }
      }
    ],
    "isActive": true,
    "id": "wf_1768156586608_p5h1llwl8",
    "createdAt": "2026-01-11T18:36:26.608Z",
    "updatedAt": "2026-01-11T18:36:26.608Z"
  },
  {
    "name": "Workflow 1768156588143",
    "description": "",
    "trigger": {
      "type": "webhook",
      "config": {
        "url": ""
      }
    },
    "actions": [
      {
        "id": "action_1",
        "type": "email",
        "config": {
          "to": "samptv59@gmail.com",
          "subject": "adwda",
          "body": "ddd",
          "from": ""
        },
        "position": {
          "x": 100,
          "y": 100
        }
      }
    ],
    "isActive": true,
    "id": "wf_1768156588150_tlradgbe8",
    "createdAt": "2026-01-11T18:36:28.150Z",
    "updatedAt": "2026-01-11T18:36:28.150Z"
  },
  {
    "name": "Workflow 1768156588169",
    "description": "",
    "trigger": {
      "type": "webhook",
      "config": {
        "url": ""
      }
    },
    "actions": [
      {
        "id": "action_1",
        "type": "email",
        "config": {
          "to": "samptv59@gmail.com",
          "subject": "adwda",
          "body": "ddd",
          "from": ""
        },
        "position": {
          "x": 100,
          "y": 100
        }
      }
    ],
    "isActive": true,
    "id": "wf_1768156588175_fksk5y4kn",
    "createdAt": "2026-01-11T18:36:28.175Z",
    "updatedAt": "2026-01-11T18:36:28.175Z"
  },
  {
    "name": "Test DB Workflow",
    "description": "Testing database operations",
    "trigger": {
      "id": "trigger_1",
      "type": "webhook",
      "config": {
        "url": "",
        "method": "POST",
        "headers": {}
      }
    },
    "actions": [
      {
        "id": "action_1",
        "type": "database",
        "config": {
          "operation": "insert",
          "table": "test_users",
          "data": {
            "name": "Test User from Workflow",
            "email": "workflow@test.com",
            "status": "active"
          }
        }
      }
    ],
    "id": "wf_1768165800246_19uaqhw2v",
    "createdAt": "2026-01-11T21:10:00.246Z",
    "updatedAt": "2026-01-11T21:10:00.246Z"
  },
  {
    "name": "",
    "description": "",
    "trigger": {
      "id": "trigger_1",
      "type": "webhook",
      "config": {
        "url": "",
        "method": "POST",
        "headers": {}
      }
    },
    "actions": [
      {
        "id": "action_1",
        "type": "database",
        "config": {
          "operation": "insert",
          "table": "test_users",
          "data": {
            "name": "Новый Пользователь из Workflow",
            "email": "workflow@example.com",
            "status": "active"
          }
        },
        "position": {
          "x": 100,
          "y": 100
        }
      }
    ],
    "id": "wf_1768167461748_fkea2j575",
    "createdAt": "2026-01-11T21:37:41.748Z",
    "updatedAt": "2026-01-11T21:37:41.748Z"
  },
  {
    "name": "",
    "description": "",
    "trigger": {
      "id": "trigger_1",
      "type": "webhook",
      "config": {
        "url": "",
        "method": "POST",
        "headers": {}
      }
    },
    "actions": [
      {
        "id": "action_1",
        "type": "database",
        "config": {
          "operation": "insert",
          "table": "test_users",
          "data": {
            "name": "Новый Пользователь из Workflow",
            "email": "workflow@example.com",
            "status": "active"
          }
        },
        "position": {
          "x": 100,
          "y": 100
        }
      }
    ],
    "id": "wf_1768167463320_45190venh",
    "createdAt": "2026-01-11T21:37:43.320Z",
    "updatedAt": "2026-01-11T21:37:43.320Z"
  },
  {
    "name": "",
    "description": "",
    "trigger": {
      "id": "trigger_1",
      "type": "webhook",
      "config": {
        "url": "",
        "method": "POST",
        "headers": {}
      }
    },
    "actions": [
      {
        "id": "action_1",
        "type": "database",
        "config": {
          "operation": "insert",
          "table": "test_users",
          "data": {
            "name": "Новый Пользователь из Workflow",
            "email": "workflow@example.com",
            "status": "active"
          }
        },
        "position": {
          "x": 100,
          "y": 100
        }
      }
    ],
    "id": "wf_1768167470965_kxuv89vtd",
    "createdAt": "2026-01-11T21:37:50.965Z",
    "updatedAt": "2026-01-11T21:37:50.965Z"
  },
  {
    "name": "",
    "description": "",
    "trigger": {
      "id": "trigger_1",
      "type": "webhook",
      "config": {
        "url": "",
        "method": "POST",
        "headers": {}
      }
    },
    "actions": [
      {
        "id": "action_1",
        "type": "database",
        "config": {
          "operation": "insert",
          "table": "test_users",
          "data": {
            "name": "Новый Пользователь из Workflow",
            "email": "workflow@example.com",
            "status": "active"
          }
        },
        "position": {
          "x": 100,
          "y": 100
        }
      }
    ],
    "id": "wf_1768167498344_qlw48phk2",
    "createdAt": "2026-01-11T21:38:18.344Z",
    "updatedAt": "2026-01-11T21:38:18.344Z"
  },
  {
    "name": "",
    "description": "",
    "trigger": {
      "id": "trigger_1",
      "type": "webhook",
      "config": {
        "url": "",
        "method": "POST",
        "headers": {}
      }
    },
    "actions": [
      {
        "id": "action_2",
        "type": "database",
        "config": {
          "operation": "insert",
          "table": "test_users",
          "data": {
            "name": "Новый Пользователь из Workflow3123123",
            "email": "workflow@example.com",
            "status": "active"
          }
        },
        "position": {
          "x": 100,
          "y": 100
        }
      }
    ],
    "id": "wf_1768167532273_12n09oex3",
    "createdAt": "2026-01-11T21:38:52.273Z",
    "updatedAt": "2026-01-11T21:38:52.273Z"
  },
  {
    "name": "",
    "description": "",
    "trigger": {
      "id": "trigger_1",
      "type": "webhook",
      "config": {
        "url": "",
        "method": "POST",
        "headers": {}
      }
    },
    "actions": [
      {
        "id": "action_2",
        "type": "database",
        "config": {
          "operation": "insert",
          "table": "test_users",
          "data": {
            "name": "Новый Пользователь из Workflow3123123",
            "email": "workflow@gmail.com",
            "status": "active"
          }
        },
        "position": {
          "x": 100,
          "y": 100
        }
      }
    ],
    "id": "wf_1768167555265_57uj1ecqb",
    "createdAt": "2026-01-11T21:39:15.265Z",
    "updatedAt": "2026-01-11T21:39:15.265Z"
  },
  {
    "name": "Workflow 1768167588100",
    "description": "",
    "trigger": {
      "id": "trigger_1",
      "type": "webhook",
      "config": {
        "url": "",
        "method": "POST",
        "headers": {}
      }
    },
    "actions": [
      {
        "id": "action_2",
        "type": "database",
        "config": {
          "operation": "insert",
          "table": "test_users",
          "data": {
            "name": "Новый Пользователь из Workflow3123123",
            "email": "workflow@gmail.com",
            "status": "active"
          }
        },
        "position": {
          "x": 100,
          "y": 100
        }
      }
    ],
    "isActive": true,
    "id": "wf_1768167588107_pdt5bklj5",
    "createdAt": "2026-01-11T21:39:48.107Z",
    "updatedAt": "2026-01-11T21:39:48.107Z"
  },
  {
    "name": "Workflow 1768167589134",
    "description": "",
    "trigger": {
      "id": "trigger_1",
      "type": "webhook",
      "config": {
        "url": "",
        "method": "POST",
        "headers": {}
      }
    },
    "actions": [
      {
        "id": "action_2",
        "type": "database",
        "config": {
          "operation": "insert",
          "table": "test_users",
          "data": {
            "name": "Новый Пользователь из Workflow3123123",
            "email": "workflow@gmail.com",
            "status": "active"
          }
        },
        "position": {
          "x": 100,
          "y": 100
        }
      }
    ],
    "isActive": true,
    "id": "wf_1768167589140_1d4fg7g8v",
    "createdAt": "2026-01-11T21:39:49.140Z",
    "updatedAt": "2026-01-11T21:39:49.140Z"
  },
  {
    "name": "Workflow 1768167589734",
    "description": "",
    "trigger": {
      "id": "trigger_1",
      "type": "webhook",
      "config": {
        "url": "",
        "method": "POST",
        "headers": {}
      }
    },
    "actions": [
      {
        "id": "action_2",
        "type": "database",
        "config": {
          "operation": "insert",
          "table": "test_users",
          "data": {
            "name": "Новый Пользователь из Workflow3123123",
            "email": "workflow@gmail.com",
            "status": "active"
          }
        },
        "position": {
          "x": 100,
          "y": 100
        }
      }
    ],
    "isActive": true,
    "id": "wf_1768167589740_kh94l0hqe",
    "createdAt": "2026-01-11T21:39:49.740Z",
    "updatedAt": "2026-01-11T21:39:49.740Z"
  },
  {
    "name": "Workflow 1768167590167",
    "description": "",
    "trigger": {
      "id": "trigger_1",
      "type": "webhook",
      "config": {
        "url": "",
        "method": "POST",
        "headers": {}
      }
    },
    "actions": [
      {
        "id": "action_2",
        "type": "database",
        "config": {
          "operation": "insert",
          "table": "test_users",
          "data": {
            "name": "Новый Пользователь из Workflow3123123",
            "email": "workflow@gmail.com",
            "status": "active"
          }
        },
        "position": {
          "x": 100,
          "y": 100
        }
      }
    ],
    "isActive": true,
    "id": "wf_1768167590177_l01tkw1we",
    "createdAt": "2026-01-11T21:39:50.177Z",
    "updatedAt": "2026-01-11T21:39:50.177Z"
  },
  {
    "name": "Workflow 1768167590398",
    "description": "",
    "trigger": {
      "id": "trigger_1",
      "type": "webhook",
      "config": {
        "url": "",
        "method": "POST",
        "headers": {}
      }
    },
    "actions": [
      {
        "id": "action_2",
        "type": "database",
        "config": {
          "operation": "insert",
          "table": "test_users",
          "data": {
            "name": "Новый Пользователь из Workflow3123123",
            "email": "workflow@gmail.com",
            "status": "active"
          }
        },
        "position": {
          "x": 100,
          "y": 100
        }
      }
    ],
    "isActive": true,
    "id": "wf_1768167590411_f7np7zyl6",
    "createdAt": "2026-01-11T21:39:50.411Z",
    "updatedAt": "2026-01-11T21:39:50.411Z"
  },
  {
    "name": "Workflow 1768167590567",
    "description": "",
    "trigger": {
      "id": "trigger_1",
      "type": "webhook",
      "config": {
        "url": "",
        "method": "POST",
        "headers": {}
      }
    },
    "actions": [
      {
        "id": "action_2",
        "type": "database",
        "config": {
          "operation": "insert",
          "table": "test_users",
          "data": {
            "name": "Новый Пользователь из Workflow3123123",
            "email": "workflow@gmail.com",
            "status": "active"
          }
        },
        "position": {
          "x": 100,
          "y": 100
        }
      }
    ],
    "isActive": true,
    "id": "wf_1768167590630_26bom5njm",
    "createdAt": "2026-01-11T21:39:50.630Z",
    "updatedAt": "2026-01-11T21:39:50.630Z"
  },
  {
    "name": "Workflow 1768167590767",
    "description": "",
    "trigger": {
      "id": "trigger_1",
      "type": "webhook",
      "config": {
        "url": "",
        "method": "POST",
        "headers": {}
      }
    },
    "actions": [
      {
        "id": "action_2",
        "type": "database",
        "config": {
          "operation": "insert",
          "table": "test_users",
          "data": {
            "name": "Новый Пользователь из Workflow3123123",
            "email": "workflow@gmail.com",
            "status": "active"
          }
        },
        "position": {
          "x": 100,
          "y": 100
        }
      }
    ],
    "isActive": true,
    "id": "wf_1768167590870_hxnd29csn",
    "createdAt": "2026-01-11T21:39:50.870Z",
    "updatedAt": "2026-01-11T21:39:50.870Z"
  },
  {
    "name": "Workflow 1768167590999",
    "description": "",
    "trigger": {
      "id": "trigger_1",
      "type": "webhook",
      "config": {
        "url": "",
        "method": "POST",
        "headers": {}
      }
    },
    "actions": [
      {
        "id": "action_2",
        "type": "database",
        "config": {
          "operation": "insert",
          "table": "test_users",
          "data": {
            "name": "Новый Пользователь из Workflow3123123",
            "email": "workflow@gmail.com",
            "status": "active"
          }
        },
        "position": {
          "x": 100,
          "y": 100
        }
      }
    ],
    "isActive": true,
    "id": "wf_1768167591107_mwgh0faxf",
    "createdAt": "2026-01-11T21:39:51.107Z",
    "updatedAt": "2026-01-11T21:39:51.107Z"
  },
  {
    "name": "Workflow 1768167591199",
    "description": "",
    "trigger": {
      "id": "trigger_1",
      "type": "webhook",
      "config": {
        "url": "",
        "method": "POST",
        "headers": {}
      }
    },
    "actions": [
      {
        "id": "action_2",
        "type": "database",
        "config": {
          "operation": "insert",
          "table": "test_users",
          "data": {
            "name": "Новый Пользователь из Workflow3123123",
            "email": "workflow@gmail.com",
            "status": "active"
          }
        },
        "position": {
          "x": 100,
          "y": 100
        }
      }
    ],
    "isActive": true,
    "id": "wf_1768167591346_7soch3og7",
    "createdAt": "2026-01-11T21:39:51.346Z",
    "updatedAt": "2026-01-11T21:39:51.346Z"
  },
  {
    "name": "Workflow 1768167591434",
    "description": "",
    "trigger": {
      "id": "trigger_1",
      "type": "webhook",
      "config": {
        "url": "",
        "method": "POST",
        "headers": {}
      }
    },
    "actions": [
      {
        "id": "action_2",
        "type": "database",
        "config": {
          "operation": "insert",
          "table": "test_users",
          "data": {
            "name": "Новый Пользователь из Workflow3123123",
            "email": "workflow@gmail.com",
            "status": "active"
          }
        },
        "position": {
          "x": 100,
          "y": 100
        }
      }
    ],
    "isActive": true,
    "id": "wf_1768167591576_ye1i6chki",
    "createdAt": "2026-01-11T21:39:51.576Z",
    "updatedAt": "2026-01-11T21:39:51.576Z"
  },
  {
    "name": "Workflow 1768167591595",
    "description": "",
    "trigger": {
      "id": "trigger_1",
      "type": "webhook",
      "config": {
        "url": "",
        "method": "POST",
        "headers": {}
      }
    },
    "actions": [
      {
        "id": "action_2",
        "type": "database",
        "config": {
          "operation": "insert",
          "table": "test_users",
          "data": {
            "name": "Новый Пользователь из Workflow3123123",
            "email": "workflow@gmail.com",
            "status": "active"
          }
        },
        "position": {
          "x": 100,
          "y": 100
        }
      }
    ],
    "isActive": true,
    "id": "wf_1768167591601_slwo413o5",
    "createdAt": "2026-01-11T21:39:51.601Z",
    "updatedAt": "2026-01-11T21:39:51.601Z"
  },
  {
    "name": "Workflow 1768167591650",
    "description": "",
    "trigger": {
      "id": "trigger_1",
      "type": "webhook",
      "config": {
        "url": "",
        "method": "POST",
        "headers": {}
      }
    },
    "actions": [
      {
        "id": "action_2",
        "type": "database",
        "config": {
          "operation": "insert",
          "table": "test_users",
          "data": {
            "name": "Новый Пользователь из Workflow3123123",
            "email": "workflow@gmail.com",
            "status": "active"
          }
        },
        "position": {
          "x": 100,
          "y": 100
        }
      }
    ],
    "isActive": true,
    "id": "wf_1768167591792_q1rk0nl3q",
    "createdAt": "2026-01-11T21:39:51.792Z",
    "updatedAt": "2026-01-11T21:39:51.792Z"
  },
  {
    "name": "Workflow 1768167591813",
    "description": "",
    "trigger": {
      "id": "trigger_1",
      "type": "webhook",
      "config": {
        "url": "",
        "method": "POST",
        "headers": {}
      }
    },
    "actions": [
      {
        "id": "action_2",
        "type": "database",
        "config": {
          "operation": "insert",
          "table": "test_users",
          "data": {
            "name": "Новый Пользователь из Workflow3123123",
            "email": "workflow@gmail.com",
            "status": "active"
          }
        },
        "position": {
          "x": 100,
          "y": 100
        }
      }
    ],
    "isActive": true,
    "id": "wf_1768167591819_7ebcjsfhs",
    "createdAt": "2026-01-11T21:39:51.819Z",
    "updatedAt": "2026-01-11T21:39:51.819Z"
  },
  {
    "name": "Workflow 1768167591900",
    "description": "",
    "trigger": {
      "id": "trigger_1",
      "type": "webhook",
      "config": {
        "url": "",
        "method": "POST",
        "headers": {}
      }
    },
    "actions": [
      {
        "id": "action_2",
        "type": "database",
        "config": {
          "operation": "insert",
          "table": "test_users",
          "data": {
            "name": "Новый Пользователь из Workflow3123123",
            "email": "workflow@gmail.com",
            "status": "active"
          }
        },
        "position": {
          "x": 100,
          "y": 100
        }
      }
    ],
    "isActive": true,
    "id": "wf_1768167592023_bu5j4bpo6",
    "createdAt": "2026-01-11T21:39:52.023Z",
    "updatedAt": "2026-01-11T21:39:52.023Z"
  },
  {
    "name": "Workflow 1768167592037",
    "description": "",
    "trigger": {
      "id": "trigger_1",
      "type": "webhook",
      "config": {
        "url": "",
        "method": "POST",
        "headers": {}
      }
    },
    "actions": [
      {
        "id": "action_2",
        "type": "database",
        "config": {
          "operation": "insert",
          "table": "test_users",
          "data": {
            "name": "Новый Пользователь из Workflow3123123",
            "email": "workflow@gmail.com",
            "status": "active"
          }
        },
        "position": {
          "x": 100,
          "y": 100
        }
      }
    ],
    "isActive": true,
    "id": "wf_1768167592041_el2iqg9c6",
    "createdAt": "2026-01-11T21:39:52.041Z",
    "updatedAt": "2026-01-11T21:39:52.041Z"
  },
  {
    "name": "Workflow 1768167592126",
    "description": "",
    "trigger": {
      "id": "trigger_1",
      "type": "webhook",
      "config": {
        "url": "",
        "method": "POST",
        "headers": {}
      }
    },
    "actions": [
      {
        "id": "action_2",
        "type": "database",
        "config": {
          "operation": "insert",
          "table": "test_users",
          "data": {
            "name": "Новый Пользователь из Workflow3123123",
            "email": "workflow@gmail.com",
            "status": "active"
          }
        },
        "position": {
          "x": 100,
          "y": 100
        }
      }
    ],
    "isActive": true,
    "id": "wf_1768167592239_vtw9owkpd",
    "createdAt": "2026-01-11T21:39:52.239Z",
    "updatedAt": "2026-01-11T21:39:52.239Z"
  },
  {
    "name": "Workflow 1768167723620",
    "description": "",
    "trigger": {
      "id": "trigger_1",
      "type": "webhook",
      "config": {
        "url": "",
        "method": "POST",
        "headers": {}
      }
    },
    "actions": [
      {
        "id": "action_1",
        "type": "database",
        "config": {
          "operation": "insert",
          "table": "test_users",
          "data": {
            "name": "прывет",
            "email": "workflow22@example.com",
            "status": "active"
          }
        },
        "position": {
          "x": 100,
          "y": 100
        }
      }
    ],
    "isActive": true,
    "id": "wf_1768167723632_3q27hxug5",
    "createdAt": "2026-01-11T21:42:03.632Z",
    "updatedAt": "2026-01-11T21:42:03.632Z"
  },
  {
    "name": "Workflow 1768167724668",
    "description": "",
    "trigger": {
      "id": "trigger_1",
      "type": "webhook",
      "config": {
        "url": "",
        "method": "POST",
        "headers": {}
      }
    },
    "actions": [
      {
        "id": "action_1",
        "type": "database",
        "config": {
          "operation": "insert",
          "table": "test_users",
          "data": {
            "name": "прывет",
            "email": "workflow22@example.com",
            "status": "active"
          }
        },
        "position": {
          "x": 100,
          "y": 100
        }
      }
    ],
    "isActive": true,
    "id": "wf_1768167724669_uvykzaman",
    "createdAt": "2026-01-11T21:42:04.669Z",
    "updatedAt": "2026-01-11T21:42:04.669Z"
  },
  {
    "name": "Workflow 1768167725120",
    "description": "",
    "trigger": {
      "id": "trigger_1",
      "type": "webhook",
      "config": {
        "url": "",
        "method": "POST",
        "headers": {}
      }
    },
    "actions": [
      {
        "id": "action_1",
        "type": "database",
        "config": {
          "operation": "insert",
          "table": "test_users",
          "data": {
            "name": "прывет",
            "email": "workflow22@example.com",
            "status": "active"
          }
        },
        "position": {
          "x": 100,
          "y": 100
        }
      }
    ],
    "isActive": true,
    "id": "wf_1768167725127_8mblbldcs",
    "createdAt": "2026-01-11T21:42:05.127Z",
    "updatedAt": "2026-01-11T21:42:05.127Z"
  },
  {
    "name": "Workflow 1768167725698",
    "description": "",
    "trigger": {
      "id": "trigger_1",
      "type": "webhook",
      "config": {
        "url": "",
        "method": "POST",
        "headers": {}
      }
    },
    "actions": [
      {
        "id": "action_1",
        "type": "database",
        "config": {
          "operation": "insert",
          "table": "test_users",
          "data": {
            "name": "прывет",
            "email": "workflow22@example.com",
            "status": "active"
          }
        },
        "position": {
          "x": 100,
          "y": 100
        }
      }
    ],
    "isActive": true,
    "id": "wf_1768167725696_ygu41xx5r",
    "createdAt": "2026-01-11T21:42:05.696Z",
    "updatedAt": "2026-01-11T21:42:05.696Z"
  },
  {
    "name": "Workflow 1768167725936",
    "description": "",
    "trigger": {
      "id": "trigger_1",
      "type": "webhook",
      "config": {
        "url": "",
        "method": "POST",
        "headers": {}
      }
    },
    "actions": [
      {
        "id": "action_1",
        "type": "database",
        "config": {
          "operation": "insert",
          "table": "test_users",
          "data": {
            "name": "прывет",
            "email": "workflow22@example.com",
            "status": "active"
          }
        },
        "position": {
          "x": 100,
          "y": 100
        }
      }
    ],
    "isActive": true,
    "id": "wf_1768167725933_j67ck45u1",
    "createdAt": "2026-01-11T21:42:05.933Z",
    "updatedAt": "2026-01-11T21:42:05.933Z"
  },
  {
    "name": "Workflow 1768167726171",
    "description": "",
    "trigger": {
      "id": "trigger_1",
      "type": "webhook",
      "config": {
        "url": "",
        "method": "POST",
        "headers": {}
      }
    },
    "actions": [
      {
        "id": "action_1",
        "type": "database",
        "config": {
          "operation": "insert",
          "table": "test_users",
          "data": {
            "name": "прывет",
            "email": "workflow22@example.com",
            "status": "active"
          }
        },
        "position": {
          "x": 100,
          "y": 100
        }
      }
    ],
    "isActive": true,
    "id": "wf_1768167726168_0pnm14j3z",
    "createdAt": "2026-01-11T21:42:06.168Z",
    "updatedAt": "2026-01-11T21:42:06.168Z"
  },
  {
    "name": "Workflow 1768167726367",
    "description": "",
    "trigger": {
      "id": "trigger_1",
      "type": "webhook",
      "config": {
        "url": "",
        "method": "POST",
        "headers": {}
      }
    },
    "actions": [
      {
        "id": "action_1",
        "type": "database",
        "config": {
          "operation": "insert",
          "table": "test_users",
          "data": {
            "name": "прывет",
            "email": "workflow22@example.com",
            "status": "active"
          }
        },
        "position": {
          "x": 100,
          "y": 100
        }
      }
    ],
    "isActive": true,
    "id": "wf_1768167726380_wof2o1ggi",
    "createdAt": "2026-01-11T21:42:06.380Z",
    "updatedAt": "2026-01-11T21:42:06.380Z"
  },
  {
    "name": "Workflow 1768167726729",
    "description": "",
    "trigger": {
      "id": "trigger_1",
      "type": "webhook",
      "config": {
        "url": "",
        "method": "POST",
        "headers": {}
      }
    },
    "actions": [
      {
        "id": "action_1",
        "type": "database",
        "config": {
          "operation": "insert",
          "table": "test_users",
          "data": {
            "name": "прывет",
            "email": "workflow22@example.com",
            "status": "active"
          }
        },
        "position": {
          "x": 100,
          "y": 100
        }
      }
    ],
    "isActive": true,
    "id": "wf_1768167726726_329fsiw70",
    "createdAt": "2026-01-11T21:42:06.726Z",
    "updatedAt": "2026-01-11T21:42:06.726Z"
  },
  {
    "name": "Workflow 1768167726932",
    "description": "",
    "trigger": {
      "id": "trigger_1",
      "type": "webhook",
      "config": {
        "url": "",
        "method": "POST",
        "headers": {}
      }
    },
    "actions": [
      {
        "id": "action_1",
        "type": "database",
        "config": {
          "operation": "insert",
          "table": "test_users",
          "data": {
            "name": "прывет",
            "email": "workflow22@example.com",
            "status": "active"
          }
        },
        "position": {
          "x": 100,
          "y": 100
        }
      }
    ],
    "isActive": true,
    "id": "wf_1768167726932_57j80nyo2",
    "createdAt": "2026-01-11T21:42:06.932Z",
    "updatedAt": "2026-01-11T21:42:06.932Z"
  },
  {
    "name": "Workflow 1768167726966",
    "description": "",
    "trigger": {
      "id": "trigger_1",
      "type": "webhook",
      "config": {
        "url": "",
        "method": "POST",
        "headers": {}
      }
    },
    "actions": [
      {
        "id": "action_1",
        "type": "database",
        "config": {
          "operation": "insert",
          "table": "test_users",
          "data": {
            "name": "прывет",
            "email": "workflow22@example.com",
            "status": "active"
          }
        },
        "position": {
          "x": 100,
          "y": 100
        }
      }
    ],
    "isActive": true,
    "id": "wf_1768167726963_6qrm4fpht",
    "createdAt": "2026-01-11T21:42:06.963Z",
    "updatedAt": "2026-01-11T21:42:06.963Z"
  },
  {
    "name": "Workflow 1768167727174",
    "description": "",
    "trigger": {
      "id": "trigger_1",
      "type": "webhook",
      "config": {
        "url": "",
        "method": "POST",
        "headers": {}
      }
    },
    "actions": [
      {
        "id": "action_1",
        "type": "database",
        "config": {
          "operation": "insert",
          "table": "test_users",
          "data": {
            "name": "прывет",
            "email": "workflow22@example.com",
            "status": "active"
          }
        },
        "position": {
          "x": 100,
          "y": 100
        }
      }
    ],
    "isActive": true,
    "id": "wf_1768167727171_27sspo1yc",
    "createdAt": "2026-01-11T21:42:07.171Z",
    "updatedAt": "2026-01-11T21:42:07.171Z"
  },
  {
    "name": "Workflow 1768167727206",
    "description": "",
    "trigger": {
      "id": "trigger_1",
      "type": "webhook",
      "config": {
        "url": "",
        "method": "POST",
        "headers": {}
      }
    },
    "actions": [
      {
        "id": "action_1",
        "type": "database",
        "config": {
          "operation": "insert",
          "table": "test_users",
          "data": {
            "name": "прывет",
            "email": "workflow22@example.com",
            "status": "active"
          }
        },
        "position": {
          "x": 100,
          "y": 100
        }
      }
    ],
    "isActive": true,
    "id": "wf_1768167727203_1ohd3z3l1",
    "createdAt": "2026-01-11T21:42:07.203Z",
    "updatedAt": "2026-01-11T21:42:07.203Z"
  },
  {
    "name": "Workflow 1768167727421",
    "description": "",
    "trigger": {
      "id": "trigger_1",
      "type": "webhook",
      "config": {
        "url": "",
        "method": "POST",
        "headers": {}
      }
    },
    "actions": [
      {
        "id": "action_1",
        "type": "database",
        "config": {
          "operation": "insert",
          "table": "test_users",
          "data": {
            "name": "прывет",
            "email": "workflow22@example.com",
            "status": "active"
          }
        },
        "position": {
          "x": 100,
          "y": 100
        }
      }
    ],
    "isActive": true,
    "id": "wf_1768167727418_iy3vnuu05",
    "createdAt": "2026-01-11T21:42:07.418Z",
    "updatedAt": "2026-01-11T21:42:07.418Z"
  },
  {
    "name": "Workflow 1768167727751",
    "description": "",
    "trigger": {
      "id": "trigger_1",
      "type": "webhook",
      "config": {
        "url": "",
        "method": "POST",
        "headers": {}
      }
    },
    "actions": [
      {
        "id": "action_1",
        "type": "database",
        "config": {
          "operation": "insert",
          "table": "test_users",
          "data": {
            "name": "прывет",
            "email": "workflow22@example.com",
            "status": "active"
          }
        },
        "position": {
          "x": 100,
          "y": 100
        }
      }
    ],
    "isActive": true,
    "id": "wf_1768167727883_1mvx2f8sj",
    "createdAt": "2026-01-11T21:42:07.883Z",
    "updatedAt": "2026-01-11T21:42:07.883Z"
  },
  {
    "name": "Workflow 1768167727965",
    "description": "",
    "trigger": {
      "id": "trigger_1",
      "type": "webhook",
      "config": {
        "url": "",
        "method": "POST",
        "headers": {}
      }
    },
    "actions": [
      {
        "id": "action_1",
        "type": "database",
        "config": {
          "operation": "insert",
          "table": "test_users",
          "data": {
            "name": "прывет",
            "email": "workflow22@example.com",
            "status": "active"
          }
        },
        "position": {
          "x": 100,
          "y": 100
        }
      }
    ],
    "isActive": true,
    "id": "wf_1768167728229_4ndc06m8g",
    "createdAt": "2026-01-11T21:42:08.229Z",
    "updatedAt": "2026-01-11T21:42:08.229Z"
  },
  {
    "name": "Workflow 1768167727991",
    "description": "",
    "trigger": {
      "id": "trigger_1",
      "type": "webhook",
      "config": {
        "url": "",
        "method": "POST",
        "headers": {}
      }
    },
    "actions": [
      {
        "id": "action_1",
        "type": "database",
        "config": {
          "operation": "insert",
          "table": "test_users",
          "data": {
            "name": "прывет",
            "email": "workflow22@example.com",
            "status": "active"
          }
        },
        "position": {
          "x": 100,
          "y": 100
        }
      }
    ],
    "isActive": true,
    "id": "wf_1768167728236_l89hn8mah",
    "createdAt": "2026-01-11T21:42:08.236Z",
    "updatedAt": "2026-01-11T21:42:08.236Z"
  },
  {
    "name": "Workflow 1768167728168",
    "description": "",
    "trigger": {
      "id": "trigger_1",
      "type": "webhook",
      "config": {
        "url": "",
        "method": "POST",
        "headers": {}
      }
    },
    "actions": [
      {
        "id": "action_1",
        "type": "database",
        "config": {
          "operation": "insert",
          "table": "test_users",
          "data": {
            "name": "прывет",
            "email": "workflow22@example.com",
            "status": "active"
          }
        },
        "position": {
          "x": 100,
          "y": 100
        }
      }
    ],
    "isActive": true,
    "id": "wf_1768167728243_4uwmksfvz",
    "createdAt": "2026-01-11T21:42:08.243Z",
    "updatedAt": "2026-01-11T21:42:08.243Z"
  },
  {
    "name": "Workflow 1768167728198",
    "description": "",
    "trigger": {
      "id": "trigger_1",
      "type": "webhook",
      "config": {
        "url": "",
        "method": "POST",
        "headers": {}
      }
    },
    "actions": [
      {
        "id": "action_1",
        "type": "database",
        "config": {
          "operation": "insert",
          "table": "test_users",
          "data": {
            "name": "прывет",
            "email": "workflow22@example.com",
            "status": "active"
          }
        },
        "position": {
          "x": 100,
          "y": 100
        }
      }
    ],
    "isActive": true,
    "id": "wf_1768167728252_d7ikvxpji",
    "createdAt": "2026-01-11T21:42:08.252Z",
    "updatedAt": "2026-01-11T21:42:08.252Z"
  },
  {
    "name": "Workflow 1768167728415",
    "description": "",
    "trigger": {
      "id": "trigger_1",
      "type": "webhook",
      "config": {
        "url": "",
        "method": "POST",
        "headers": {}
      }
    },
    "actions": [
      {
        "id": "action_1",
        "type": "database",
        "config": {
          "operation": "insert",
          "table": "test_users",
          "data": {
            "name": "прывет",
            "email": "workflow22@example.com",
            "status": "active"
          }
        },
        "position": {
          "x": 100,
          "y": 100
        }
      }
    ],
    "isActive": true,
    "id": "wf_1768167728723_obj1dmbta",
    "createdAt": "2026-01-11T21:42:08.723Z",
    "updatedAt": "2026-01-11T21:42:08.723Z"
  },
  {
    "name": "Workflow 1768167728443",
    "description": "",
    "trigger": {
      "id": "trigger_1",
      "type": "webhook",
      "config": {
        "url": "",
        "method": "POST",
        "headers": {}
      }
    },
    "actions": [
      {
        "id": "action_1",
        "type": "database",
        "config": {
          "operation": "insert",
          "table": "test_users",
          "data": {
            "name": "прывет",
            "email": "workflow22@example.com",
            "status": "active"
          }
        },
        "position": {
          "x": 100,
          "y": 100
        }
      }
    ],
    "isActive": true,
    "id": "wf_1768167728733_yau5pxl79",
    "createdAt": "2026-01-11T21:42:08.733Z",
    "updatedAt": "2026-01-11T21:42:08.733Z"
  },
  {
    "name": "Workflow 1768167728649",
    "description": "",
    "trigger": {
      "id": "trigger_1",
      "type": "webhook",
      "config": {
        "url": "",
        "method": "POST",
        "headers": {}
      }
    },
    "actions": [
      {
        "id": "action_1",
        "type": "database",
        "config": {
          "operation": "insert",
          "table": "test_users",
          "data": {
            "name": "прывет",
            "email": "workflow22@example.com",
            "status": "active"
          }
        },
        "position": {
          "x": 100,
          "y": 100
        }
      }
    ],
    "isActive": true,
    "id": "wf_1768167728745_xfmzrrcwf",
    "createdAt": "2026-01-11T21:42:08.745Z",
    "updatedAt": "2026-01-11T21:42:08.745Z"
  },
  {
    "name": "Workflow 1768167728775",
    "description": "",
    "trigger": {
      "id": "trigger_1",
      "type": "webhook",
      "config": {
        "url": "",
        "method": "POST",
        "headers": {}
      }
    },
    "actions": [
      {
        "id": "action_1",
        "type": "database",
        "config": {
          "operation": "insert",
          "table": "test_users",
          "data": {
            "name": "прывет",
            "email": "workflow22@example.com",
            "status": "active"
          }
        },
        "position": {
          "x": 100,
          "y": 100
        }
      }
    ],
    "isActive": true,
    "id": "wf_1768167728773_eubz1zpa4",
    "createdAt": "2026-01-11T21:42:08.773Z",
    "updatedAt": "2026-01-11T21:42:08.773Z"
  },
  {
    "name": "Workflow 1768167728916",
    "description": "",
    "trigger": {
      "id": "trigger_1",
      "type": "webhook",
      "config": {
        "url": "",
        "method": "POST",
        "headers": {}
      }
    },
    "actions": [
      {
        "id": "action_1",
        "type": "database",
        "config": {
          "operation": "insert",
          "table": "test_users",
          "data": {
            "name": "прывет",
            "email": "workflow22@example.com",
            "status": "active"
          }
        },
        "position": {
          "x": 100,
          "y": 100
        }
      }
    ],
    "isActive": true,
    "id": "wf_1768167729222_479zpafqg",
    "createdAt": "2026-01-11T21:42:09.222Z",
    "updatedAt": "2026-01-11T21:42:09.222Z"
  },
  {
    "name": "Workflow 1768167728982",
    "description": "",
    "trigger": {
      "id": "trigger_1",
      "type": "webhook",
      "config": {
        "url": "",
        "method": "POST",
        "headers": {}
      }
    },
    "actions": [
      {
        "id": "action_1",
        "type": "database",
        "config": {
          "operation": "insert",
          "table": "test_users",
          "data": {
            "name": "прывет",
            "email": "workflow22@example.com",
            "status": "active"
          }
        },
        "position": {
          "x": 100,
          "y": 100
        }
      }
    ],
    "isActive": true,
    "id": "wf_1768167729230_eduf0vrz1",
    "createdAt": "2026-01-11T21:42:09.230Z",
    "updatedAt": "2026-01-11T21:42:09.230Z"
  },
  {
    "name": "Workflow 1768167729091",
    "description": "",
    "trigger": {
      "id": "trigger_1",
      "type": "webhook",
      "config": {
        "url": "",
        "method": "POST",
        "headers": {}
      }
    },
    "actions": [
      {
        "id": "action_1",
        "type": "database",
        "config": {
          "operation": "insert",
          "table": "test_users",
          "data": {
            "name": "прывет",
            "email": "workflow22@example.com",
            "status": "active"
          }
        },
        "position": {
          "x": 100,
          "y": 100
        }
      }
    ],
    "isActive": true,
    "id": "wf_1768167729237_o9beq0qxc",
    "createdAt": "2026-01-11T21:42:09.237Z",
    "updatedAt": "2026-01-11T21:42:09.237Z"
  },
  {
    "name": "Workflow 1768167729199",
    "description": "",
    "trigger": {
      "id": "trigger_1",
      "type": "webhook",
      "config": {
        "url": "",
        "method": "POST",
        "headers": {}
      }
    },
    "actions": [
      {
        "id": "action_1",
        "type": "database",
        "config": {
          "operation": "insert",
          "table": "test_users",
          "data": {
            "name": "прывет",
            "email": "workflow22@example.com",
            "status": "active"
          }
        },
        "position": {
          "x": 100,
          "y": 100
        }
      }
    ],
    "isActive": true,
    "id": "wf_1768167729246_704cxon9e",
    "createdAt": "2026-01-11T21:42:09.246Z",
    "updatedAt": "2026-01-11T21:42:09.246Z"
  },
  {
    "name": "Workflow 1768167729251",
    "description": "",
    "trigger": {
      "id": "trigger_1",
      "type": "webhook",
      "config": {
        "url": "",
        "method": "POST",
        "headers": {}
      }
    },
    "actions": [
      {
        "id": "action_1",
        "type": "database",
        "config": {
          "operation": "insert",
          "table": "test_users",
          "data": {
            "name": "прывет",
            "email": "workflow22@example.com",
            "status": "active"
          }
        },
        "position": {
          "x": 100,
          "y": 100
        }
      }
    ],
    "isActive": true,
    "id": "wf_1768167729716_w7b106qjk",
    "createdAt": "2026-01-11T21:42:09.716Z",
    "updatedAt": "2026-01-11T21:42:09.716Z"
  },
  {
    "name": "Workflow 1768167729459",
    "description": "",
    "trigger": {
      "id": "trigger_1",
      "type": "webhook",
      "config": {
        "url": "",
        "method": "POST",
        "headers": {}
      }
    },
    "actions": [
      {
        "id": "action_1",
        "type": "database",
        "config": {
          "operation": "insert",
          "table": "test_users",
          "data": {
            "name": "прывет",
            "email": "workflow22@example.com",
            "status": "active"
          }
        },
        "position": {
          "x": 100,
          "y": 100
        }
      }
    ],
    "isActive": true,
    "id": "wf_1768167729727_55731p3np",
    "createdAt": "2026-01-11T21:42:09.727Z",
    "updatedAt": "2026-01-11T21:42:09.727Z"
  },
  {
    "name": "Workflow 1768167729487",
    "description": "",
    "trigger": {
      "id": "trigger_1",
      "type": "webhook",
      "config": {
        "url": "",
        "method": "POST",
        "headers": {}
      }
    },
    "actions": [
      {
        "id": "action_1",
        "type": "database",
        "config": {
          "operation": "insert",
          "table": "test_users",
          "data": {
            "name": "прывет",
            "email": "workflow22@example.com",
            "status": "active"
          }
        },
        "position": {
          "x": 100,
          "y": 100
        }
      }
    ],
    "isActive": true,
    "id": "wf_1768167729738_svd0fcd85",
    "createdAt": "2026-01-11T21:42:09.738Z",
    "updatedAt": "2026-01-11T21:42:09.738Z"
  },
  {
    "name": "Workflow 1768167729683",
    "description": "",
    "trigger": {
      "id": "trigger_1",
      "type": "webhook",
      "config": {
        "url": "",
        "method": "POST",
        "headers": {}
      }
    },
    "actions": [
      {
        "id": "action_1",
        "type": "database",
        "config": {
          "operation": "insert",
          "table": "test_users",
          "data": {
            "name": "прывет",
            "email": "workflow22@example.com",
            "status": "active"
          }
        },
        "position": {
          "x": 100,
          "y": 100
        }
      }
    ],
    "isActive": true,
    "id": "wf_1768167730222_m7a4tmqsz",
    "createdAt": "2026-01-11T21:42:10.222Z",
    "updatedAt": "2026-01-11T21:42:10.222Z"
  },
  {
    "name": "Workflow 1768167729748",
    "description": "",
    "trigger": {
      "id": "trigger_1",
      "type": "webhook",
      "config": {
        "url": "",
        "method": "POST",
        "headers": {}
      }
    },
    "actions": [
      {
        "id": "action_1",
        "type": "database",
        "config": {
          "operation": "insert",
          "table": "test_users",
          "data": {
            "name": "прывет",
            "email": "workflow22@example.com",
            "status": "active"
          }
        },
        "position": {
          "x": 100,
          "y": 100
        }
      }
    ],
    "isActive": true,
    "id": "wf_1768167730232_54iz4gnxd",
    "createdAt": "2026-01-11T21:42:10.232Z",
    "updatedAt": "2026-01-11T21:42:10.232Z"
  },
  {
    "name": "Workflow 1768167729801",
    "description": "",
    "trigger": {
      "id": "trigger_1",
      "type": "webhook",
      "config": {
        "url": "",
        "method": "POST",
        "headers": {}
      }
    },
    "actions": [
      {
        "id": "action_1",
        "type": "database",
        "config": {
          "operation": "insert",
          "table": "test_users",
          "data": {
            "name": "прывет",
            "email": "workflow22@example.com",
            "status": "active"
          }
        },
        "position": {
          "x": 100,
          "y": 100
        }
      }
    ],
    "isActive": true,
    "id": "wf_1768167730241_2tljvz82a",
    "createdAt": "2026-01-11T21:42:10.241Z",
    "updatedAt": "2026-01-11T21:42:10.241Z"
  },
  {
    "name": "Workflow 1768167729950",
    "description": "",
    "trigger": {
      "id": "trigger_1",
      "type": "webhook",
      "config": {
        "url": "",
        "method": "POST",
        "headers": {}
      }
    },
    "actions": [
      {
        "id": "action_1",
        "type": "database",
        "config": {
          "operation": "insert",
          "table": "test_users",
          "data": {
            "name": "прывет",
            "email": "workflow22@example.com",
            "status": "active"
          }
        },
        "position": {
          "x": 100,
          "y": 100
        }
      }
    ],
    "isActive": true,
    "id": "wf_1768167730872_6hoffvsd1",
    "createdAt": "2026-01-11T21:42:10.872Z",
    "updatedAt": "2026-01-11T21:42:10.872Z"
  },
  {
    "name": "Workflow 1768167729998",
    "description": "",
    "trigger": {
      "id": "trigger_1",
      "type": "webhook",
      "config": {
        "url": "",
        "method": "POST",
        "headers": {}
      }
    },
    "actions": [
      {
        "id": "action_1",
        "type": "database",
        "config": {
          "operation": "insert",
          "table": "test_users",
          "data": {
            "name": "прывет",
            "email": "workflow22@example.com",
            "status": "active"
          }
        },
        "position": {
          "x": 100,
          "y": 100
        }
      }
    ],
    "isActive": true,
    "id": "wf_1768167730879_ba5103okh",
    "createdAt": "2026-01-11T21:42:10.879Z",
    "updatedAt": "2026-01-11T21:42:10.879Z"
  },
  {
    "name": "Workflow 1768167730101",
    "description": "",
    "trigger": {
      "id": "trigger_1",
      "type": "webhook",
      "config": {
        "url": "",
        "method": "POST",
        "headers": {}
      }
    },
    "actions": [
      {
        "id": "action_1",
        "type": "database",
        "config": {
          "operation": "insert",
          "table": "test_users",
          "data": {
            "name": "прывет",
            "email": "workflow22@example.com",
            "status": "active"
          }
        },
        "position": {
          "x": 100,
          "y": 100
        }
      }
    ],
    "isActive": true,
    "id": "wf_1768167730886_r3pxysrrd",
    "createdAt": "2026-01-11T21:42:10.886Z",
    "updatedAt": "2026-01-11T21:42:10.886Z"
  },
  {
    "name": "Workflow 1768167730102",
    "description": "",
    "trigger": {
      "id": "trigger_1",
      "type": "webhook",
      "config": {
        "url": "",
        "method": "POST",
        "headers": {}
      }
    },
    "actions": [
      {
        "id": "action_1",
        "type": "database",
        "config": {
          "operation": "insert",
          "table": "test_users",
          "data": {
            "name": "прывет",
            "email": "workflow22@example.com",
            "status": "active"
          }
        },
        "position": {
          "x": 100,
          "y": 100
        }
      }
    ],
    "isActive": true,
    "id": "wf_1768167730894_pmrkccmxe",
    "createdAt": "2026-01-11T21:42:10.894Z",
    "updatedAt": "2026-01-11T21:42:10.894Z"
  },
  {
    "name": "Workflow 1768167730250",
    "description": "",
    "trigger": {
      "id": "trigger_1",
      "type": "webhook",
      "config": {
        "url": "",
        "method": "POST",
        "headers": {}
      }
    },
    "actions": [
      {
        "id": "action_1",
        "type": "database",
        "config": {
          "operation": "insert",
          "table": "test_users",
          "data": {
            "name": "прывет",
            "email": "workflow22@example.com",
            "status": "active"
          }
        },
        "position": {
          "x": 100,
          "y": 100
        }
      }
    ],
    "isActive": true,
    "id": "wf_1768167731629_g7gvbc6ty",
    "createdAt": "2026-01-11T21:42:11.629Z",
    "updatedAt": "2026-01-11T21:42:11.629Z"
  },
  {
    "name": "Workflow 1768167730280",
    "description": "",
    "trigger": {
      "id": "trigger_1",
      "type": "webhook",
      "config": {
        "url": "",
        "method": "POST",
        "headers": {}
      }
    },
    "actions": [
      {
        "id": "action_1",
        "type": "database",
        "config": {
          "operation": "insert",
          "table": "test_users",
          "data": {
            "name": "прывет",
            "email": "workflow22@example.com",
            "status": "active"
          }
        },
        "position": {
          "x": 100,
          "y": 100
        }
      }
    ],
    "isActive": true,
    "id": "wf_1768167731637_ajq39xrwg",
    "createdAt": "2026-01-11T21:42:11.637Z",
    "updatedAt": "2026-01-11T21:42:11.637Z"
  },
  {
    "name": "Workflow 1768167730455",
    "description": "",
    "trigger": {
      "id": "trigger_1",
      "type": "webhook",
      "config": {
        "url": "",
        "method": "POST",
        "headers": {}
      }
    },
    "actions": [
      {
        "id": "action_1",
        "type": "database",
        "config": {
          "operation": "insert",
          "table": "test_users",
          "data": {
            "name": "прывет",
            "email": "workflow22@example.com",
            "status": "active"
          }
        },
        "position": {
          "x": 100,
          "y": 100
        }
      }
    ],
    "isActive": true,
    "id": "wf_1768167731645_tfius4dxs",
    "createdAt": "2026-01-11T21:42:11.645Z",
    "updatedAt": "2026-01-11T21:42:11.645Z"
  },
  {
    "name": "Workflow 1768167730483",
    "description": "",
    "trigger": {
      "id": "trigger_1",
      "type": "webhook",
      "config": {
        "url": "",
        "method": "POST",
        "headers": {}
      }
    },
    "actions": [
      {
        "id": "action_1",
        "type": "database",
        "config": {
          "operation": "insert",
          "table": "test_users",
          "data": {
            "name": "прывет",
            "email": "workflow22@example.com",
            "status": "active"
          }
        },
        "position": {
          "x": 100,
          "y": 100
        }
      }
    ],
    "isActive": true,
    "id": "wf_1768167731653_lsvfypefo",
    "createdAt": "2026-01-11T21:42:11.653Z",
    "updatedAt": "2026-01-11T21:42:11.653Z"
  },
  {
    "name": "Workflow 1768167730600",
    "description": "",
    "trigger": {
      "id": "trigger_1",
      "type": "webhook",
      "config": {
        "url": "",
        "method": "POST",
        "headers": {}
      }
    },
    "actions": [
      {
        "id": "action_1",
        "type": "database",
        "config": {
          "operation": "insert",
          "table": "test_users",
          "data": {
            "name": "прывет",
            "email": "workflow22@example.com",
            "status": "active"
          }
        },
        "position": {
          "x": 100,
          "y": 100
        }
      }
    ],
    "isActive": true,
    "id": "wf_1768167731661_4qkhpbtw2",
    "createdAt": "2026-01-11T21:42:11.661Z",
    "updatedAt": "2026-01-11T21:42:11.661Z"
  },
  {
    "name": "Workflow 1768167731313",
    "description": "",
    "trigger": {
      "id": "trigger_1",
      "type": "webhook",
      "config": {
        "url": "",
        "method": "POST",
        "headers": {}
      }
    },
    "actions": [
      {
        "id": "action_1",
        "type": "database",
        "config": {
          "operation": "insert",
          "table": "test_users",
          "data": {
            "name": "прывет",
            "email": "workflow22@example.com",
            "status": "active"
          }
        },
        "position": {
          "x": 100,
          "y": 100
        }
      }
    ],
    "isActive": true,
    "id": "wf_1768167732547_f1rs10jcf",
    "createdAt": "2026-01-11T21:42:12.547Z",
    "updatedAt": "2026-01-11T21:42:12.547Z"
  },
  {
    "name": "Workflow 1768167731314",
    "description": "",
    "trigger": {
      "id": "trigger_1",
      "type": "webhook",
      "config": {
        "url": "",
        "method": "POST",
        "headers": {}
      }
    },
    "actions": [
      {
        "id": "action_1",
        "type": "database",
        "config": {
          "operation": "insert",
          "table": "test_users",
          "data": {
            "name": "прывет",
            "email": "workflow22@example.com",
            "status": "active"
          }
        },
        "position": {
          "x": 100,
          "y": 100
        }
      }
    ],
    "isActive": true,
    "id": "wf_1768167732554_dwr7e4a3a",
    "createdAt": "2026-01-11T21:42:12.554Z",
    "updatedAt": "2026-01-11T21:42:12.554Z"
  },
  {
    "name": "Workflow 1768167731314",
    "description": "",
    "trigger": {
      "id": "trigger_1",
      "type": "webhook",
      "config": {
        "url": "",
        "method": "POST",
        "headers": {}
      }
    },
    "actions": [
      {
        "id": "action_1",
        "type": "database",
        "config": {
          "operation": "insert",
          "table": "test_users",
          "data": {
            "name": "прывет",
            "email": "workflow22@example.com",
            "status": "active"
          }
        },
        "position": {
          "x": 100,
          "y": 100
        }
      }
    ],
    "isActive": true,
    "id": "wf_1768167732562_doi8dfcfx",
    "createdAt": "2026-01-11T21:42:12.562Z",
    "updatedAt": "2026-01-11T21:42:12.562Z"
  },
  {
    "name": "Workflow 1768167731314",
    "description": "",
    "trigger": {
      "id": "trigger_1",
      "type": "webhook",
      "config": {
        "url": "",
        "method": "POST",
        "headers": {}
      }
    },
    "actions": [
      {
        "id": "action_1",
        "type": "database",
        "config": {
          "operation": "insert",
          "table": "test_users",
          "data": {
            "name": "прывет",
            "email": "workflow22@example.com",
            "status": "active"
          }
        },
        "position": {
          "x": 100,
          "y": 100
        }
      }
    ],
    "isActive": true,
    "id": "wf_1768167732570_eqqspxzvr",
    "createdAt": "2026-01-11T21:42:12.570Z",
    "updatedAt": "2026-01-11T21:42:12.570Z"
  },
  {
    "name": "Workflow 1768167731339",
    "description": "",
    "trigger": {
      "id": "trigger_1",
      "type": "webhook",
      "config": {
        "url": "",
        "method": "POST",
        "headers": {}
      }
    },
    "actions": [
      {
        "id": "action_1",
        "type": "database",
        "config": {
          "operation": "insert",
          "table": "test_users",
          "data": {
            "name": "прывет",
            "email": "workflow22@example.com",
            "status": "active"
          }
        },
        "position": {
          "x": 100,
          "y": 100
        }
      }
    ],
    "isActive": true,
    "id": "wf_1768167732578_8wa7ocjie",
    "createdAt": "2026-01-11T21:42:12.578Z",
    "updatedAt": "2026-01-11T21:42:12.578Z"
  },
  {
    "name": "Workflow 1768167731340",
    "description": "",
    "trigger": {
      "id": "trigger_1",
      "type": "webhook",
      "config": {
        "url": "",
        "method": "POST",
        "headers": {}
      }
    },
    "actions": [
      {
        "id": "action_1",
        "type": "database",
        "config": {
          "operation": "insert",
          "table": "test_users",
          "data": {
            "name": "прывет",
            "email": "workflow22@example.com",
            "status": "active"
          }
        },
        "position": {
          "x": 100,
          "y": 100
        }
      }
    ],
    "isActive": true,
    "id": "wf_1768167732588_mzfnowviy",
    "createdAt": "2026-01-11T21:42:12.588Z",
    "updatedAt": "2026-01-11T21:42:12.588Z"
  },
  {
    "name": "Workflow 1768167731340",
    "description": "",
    "trigger": {
      "id": "trigger_1",
      "type": "webhook",
      "config": {
        "url": "",
        "method": "POST",
        "headers": {}
      }
    },
    "actions": [
      {
        "id": "action_1",
        "type": "database",
        "config": {
          "operation": "insert",
          "table": "test_users",
          "data": {
            "name": "прывет",
            "email": "workflow22@example.com",
            "status": "active"
          }
        },
        "position": {
          "x": 100,
          "y": 100
        }
      }
    ],
    "isActive": true,
    "id": "wf_1768167733466_vwwy7d605",
    "createdAt": "2026-01-11T21:42:13.466Z",
    "updatedAt": "2026-01-11T21:42:13.466Z"
  },
  {
    "name": "Workflow 1768167731340",
    "description": "",
    "trigger": {
      "id": "trigger_1",
      "type": "webhook",
      "config": {
        "url": "",
        "method": "POST",
        "headers": {}
      }
    },
    "actions": [
      {
        "id": "action_1",
        "type": "database",
        "config": {
          "operation": "insert",
          "table": "test_users",
          "data": {
            "name": "прывет",
            "email": "workflow22@example.com",
            "status": "active"
          }
        },
        "position": {
          "x": 100,
          "y": 100
        }
      }
    ],
    "isActive": true,
    "id": "wf_1768167733474_x9ld7r19i",
    "createdAt": "2026-01-11T21:42:13.474Z",
    "updatedAt": "2026-01-11T21:42:13.474Z"
  },
  {
    "name": "Workflow 1768167731341",
    "description": "",
    "trigger": {
      "id": "trigger_1",
      "type": "webhook",
      "config": {
        "url": "",
        "method": "POST",
        "headers": {}
      }
    },
    "actions": [
      {
        "id": "action_1",
        "type": "database",
        "config": {
          "operation": "insert",
          "table": "test_users",
          "data": {
            "name": "прывет",
            "email": "workflow22@example.com",
            "status": "active"
          }
        },
        "position": {
          "x": 100,
          "y": 100
        }
      }
    ],
    "isActive": true,
    "id": "wf_1768167733485_6m4k9hk2m",
    "createdAt": "2026-01-11T21:42:13.485Z",
    "updatedAt": "2026-01-11T21:42:13.485Z"
  },
  {
    "name": "Workflow 1768167731748",
    "description": "",
    "trigger": {
      "id": "trigger_1",
      "type": "webhook",
      "config": {
        "url": "",
        "method": "POST",
        "headers": {}
      }
    },
    "actions": [
      {
        "id": "action_1",
        "type": "database",
        "config": {
          "operation": "insert",
          "table": "test_users",
          "data": {
            "name": "прывет",
            "email": "workflow22@example.com",
            "status": "active"
          }
        },
        "position": {
          "x": 100,
          "y": 100
        }
      }
    ],
    "isActive": true,
    "id": "wf_1768167733494_8l608kgrd",
    "createdAt": "2026-01-11T21:42:13.494Z",
    "updatedAt": "2026-01-11T21:42:13.494Z"
  },
  {
    "name": "Workflow 1768167731751",
    "description": "",
    "trigger": {
      "id": "trigger_1",
      "type": "webhook",
      "config": {
        "url": "",
        "method": "POST",
        "headers": {}
      }
    },
    "actions": [
      {
        "id": "action_1",
        "type": "database",
        "config": {
          "operation": "insert",
          "table": "test_users",
          "data": {
            "name": "прывет",
            "email": "workflow22@example.com",
            "status": "active"
          }
        },
        "position": {
          "x": 100,
          "y": 100
        }
      }
    ],
    "isActive": true,
    "id": "wf_1768167733502_zonnvkmy4",
    "createdAt": "2026-01-11T21:42:13.502Z",
    "updatedAt": "2026-01-11T21:42:13.502Z"
  },
  {
    "name": "Workflow 1768167731752",
    "description": "",
    "trigger": {
      "id": "trigger_1",
      "type": "webhook",
      "config": {
        "url": "",
        "method": "POST",
        "headers": {}
      }
    },
    "actions": [
      {
        "id": "action_1",
        "type": "database",
        "config": {
          "operation": "insert",
          "table": "test_users",
          "data": {
            "name": "прывет",
            "email": "workflow22@example.com",
            "status": "active"
          }
        },
        "position": {
          "x": 100,
          "y": 100
        }
      }
    ],
    "isActive": true,
    "id": "wf_1768167733510_v0zmx33eh",
    "createdAt": "2026-01-11T21:42:13.510Z",
    "updatedAt": "2026-01-11T21:42:13.510Z"
  },
  {
    "name": "Workflow 1768167731752",
    "description": "",
    "trigger": {
      "id": "trigger_1",
      "type": "webhook",
      "config": {
        "url": "",
        "method": "POST",
        "headers": {}
      }
    },
    "actions": [
      {
        "id": "action_1",
        "type": "database",
        "config": {
          "operation": "insert",
          "table": "test_users",
          "data": {
            "name": "прывет",
            "email": "workflow22@example.com",
            "status": "active"
          }
        },
        "position": {
          "x": 100,
          "y": 100
        }
      }
    ],
    "isActive": true,
    "id": "wf_1768167734377_xbv644ri6",
    "createdAt": "2026-01-11T21:42:14.377Z",
    "updatedAt": "2026-01-11T21:42:14.377Z"
  },
  {
    "name": "Workflow 1768167731753",
    "description": "",
    "trigger": {
      "id": "trigger_1",
      "type": "webhook",
      "config": {
        "url": "",
        "method": "POST",
        "headers": {}
      }
    },
    "actions": [
      {
        "id": "action_1",
        "type": "database",
        "config": {
          "operation": "insert",
          "table": "test_users",
          "data": {
            "name": "прывет",
            "email": "workflow22@example.com",
            "status": "active"
          }
        },
        "position": {
          "x": 100,
          "y": 100
        }
      }
    ],
    "isActive": true,
    "id": "wf_1768167734387_fn0vzclh9",
    "createdAt": "2026-01-11T21:42:14.387Z",
    "updatedAt": "2026-01-11T21:42:14.387Z"
  },
  {
    "name": "Workflow 1768167732346",
    "description": "",
    "trigger": {
      "id": "trigger_1",
      "type": "webhook",
      "config": {
        "url": "",
        "method": "POST",
        "headers": {}
      }
    },
    "actions": [
      {
        "id": "action_1",
        "type": "database",
        "config": {
          "operation": "insert",
          "table": "test_users",
          "data": {
            "name": "прывет",
            "email": "workflow22@example.com",
            "status": "active"
          }
        },
        "position": {
          "x": 100,
          "y": 100
        }
      }
    ],
    "isActive": true,
    "id": "wf_1768167734396_71tk2iae5",
    "createdAt": "2026-01-11T21:42:14.396Z",
    "updatedAt": "2026-01-11T21:42:14.396Z"
  },
  {
    "name": "Workflow 1768167732373",
    "description": "",
    "trigger": {
      "id": "trigger_1",
      "type": "webhook",
      "config": {
        "url": "",
        "method": "POST",
        "headers": {}
      }
    },
    "actions": [
      {
        "id": "action_1",
        "type": "database",
        "config": {
          "operation": "insert",
          "table": "test_users",
          "data": {
            "name": "прывет",
            "email": "workflow22@example.com",
            "status": "active"
          }
        },
        "position": {
          "x": 100,
          "y": 100
        }
      }
    ],
    "isActive": true,
    "id": "wf_1768167734404_pom03n7nj",
    "createdAt": "2026-01-11T21:42:14.404Z",
    "updatedAt": "2026-01-11T21:42:14.404Z"
  },
  {
    "name": "Workflow 1768167732783",
    "description": "",
    "trigger": {
      "id": "trigger_1",
      "type": "webhook",
      "config": {
        "url": "",
        "method": "POST",
        "headers": {}
      }
    },
    "actions": [
      {
        "id": "action_1",
        "type": "database",
        "config": {
          "operation": "insert",
          "table": "test_users",
          "data": {
            "name": "прывет",
            "email": "workflow22@example.com",
            "status": "active"
          }
        },
        "position": {
          "x": 100,
          "y": 100
        }
      }
    ],
    "isActive": true,
    "id": "wf_1768167734412_kdbrgzq69",
    "createdAt": "2026-01-11T21:42:14.412Z",
    "updatedAt": "2026-01-11T21:42:14.412Z"
  },
  {
    "name": "Workflow 1768167732868",
    "description": "",
    "trigger": {
      "id": "trigger_1",
      "type": "webhook",
      "config": {
        "url": "",
        "method": "POST",
        "headers": {}
      }
    },
    "actions": [
      {
        "id": "action_1",
        "type": "database",
        "config": {
          "operation": "insert",
          "table": "test_users",
          "data": {
            "name": "прывет",
            "email": "workflow22@example.com",
            "status": "active"
          }
        },
        "position": {
          "x": 100,
          "y": 100
        }
      }
    ],
    "isActive": true,
    "id": "wf_1768167734421_xt8gyfyyp",
    "createdAt": "2026-01-11T21:42:14.421Z",
    "updatedAt": "2026-01-11T21:42:14.421Z"
  },
  {
    "name": "Workflow 1768167733367",
    "description": "",
    "trigger": {
      "id": "trigger_1",
      "type": "webhook",
      "config": {
        "url": "",
        "method": "POST",
        "headers": {}
      }
    },
    "actions": [
      {
        "id": "action_1",
        "type": "database",
        "config": {
          "operation": "insert",
          "table": "test_users",
          "data": {
            "name": "прывет",
            "email": "workflow22@example.com",
            "status": "active"
          }
        },
        "position": {
          "x": 100,
          "y": 100
        }
      }
    ],
    "isActive": true,
    "id": "wf_1768167735372_g3bb9oyyl",
    "createdAt": "2026-01-11T21:42:15.372Z",
    "updatedAt": "2026-01-11T21:42:15.372Z"
  },
  {
    "name": "Workflow 1768167733417",
    "description": "",
    "trigger": {
      "id": "trigger_1",
      "type": "webhook",
      "config": {
        "url": "",
        "method": "POST",
        "headers": {}
      }
    },
    "actions": [
      {
        "id": "action_1",
        "type": "database",
        "config": {
          "operation": "insert",
          "table": "test_users",
          "data": {
            "name": "прывет",
            "email": "workflow22@example.com",
            "status": "active"
          }
        },
        "position": {
          "x": 100,
          "y": 100
        }
      }
    ],
    "isActive": true,
    "id": "wf_1768167735384_16wikcohe",
    "createdAt": "2026-01-11T21:42:15.384Z",
    "updatedAt": "2026-01-11T21:42:15.384Z"
  },
  {
    "name": "Workflow 1768167733814",
    "description": "",
    "trigger": {
      "id": "trigger_1",
      "type": "webhook",
      "config": {
        "url": "",
        "method": "POST",
        "headers": {}
      }
    },
    "actions": [
      {
        "id": "action_1",
        "type": "database",
        "config": {
          "operation": "insert",
          "table": "test_users",
          "data": {
            "name": "прывет",
            "email": "workflow22@example.com",
            "status": "active"
          }
        },
        "position": {
          "x": 100,
          "y": 100
        }
      }
    ],
    "isActive": true,
    "id": "wf_1768167735395_t8an171co",
    "createdAt": "2026-01-11T21:42:15.395Z",
    "updatedAt": "2026-01-11T21:42:15.395Z"
  },
  {
    "name": "Workflow 1768167733934",
    "description": "",
    "trigger": {
      "id": "trigger_1",
      "type": "webhook",
      "config": {
        "url": "",
        "method": "POST",
        "headers": {}
      }
    },
    "actions": [
      {
        "id": "action_1",
        "type": "database",
        "config": {
          "operation": "insert",
          "table": "test_users",
          "data": {
            "name": "прывет",
            "email": "workflow22@example.com",
            "status": "active"
          }
        },
        "position": {
          "x": 100,
          "y": 100
        }
      }
    ],
    "isActive": true,
    "id": "wf_1768167735406_2o89ugcvo",
    "createdAt": "2026-01-11T21:42:15.406Z",
    "updatedAt": "2026-01-11T21:42:15.406Z"
  },
  {
    "name": "Workflow 1768167734393",
    "description": "",
    "trigger": {
      "id": "trigger_1",
      "type": "webhook",
      "config": {
        "url": "",
        "method": "POST",
        "headers": {}
      }
    },
    "actions": [
      {
        "id": "action_1",
        "type": "database",
        "config": {
          "operation": "insert",
          "table": "test_users",
          "data": {
            "name": "прывет",
            "email": "workflow22@example.com",
            "status": "active"
          }
        },
        "position": {
          "x": 100,
          "y": 100
        }
      }
    ],
    "isActive": true,
    "id": "wf_1768167735417_wkyotluzr",
    "createdAt": "2026-01-11T21:42:15.417Z",
    "updatedAt": "2026-01-11T21:42:15.417Z"
  },
  {
    "name": "Workflow 1768167734483",
    "description": "",
    "trigger": {
      "id": "trigger_1",
      "type": "webhook",
      "config": {
        "url": "",
        "method": "POST",
        "headers": {}
      }
    },
    "actions": [
      {
        "id": "action_1",
        "type": "database",
        "config": {
          "operation": "insert",
          "table": "test_users",
          "data": {
            "name": "прывет",
            "email": "workflow22@example.com",
            "status": "active"
          }
        },
        "position": {
          "x": 100,
          "y": 100
        }
      }
    ],
    "isActive": true,
    "id": "wf_1768167735426_877lrmbop",
    "createdAt": "2026-01-11T21:42:15.426Z",
    "updatedAt": "2026-01-11T21:42:15.426Z"
  },
  {
    "name": "Workflow 1768167734848",
    "description": "",
    "trigger": {
      "id": "trigger_1",
      "type": "webhook",
      "config": {
        "url": "",
        "method": "POST",
        "headers": {}
      }
    },
    "actions": [
      {
        "id": "action_1",
        "type": "database",
        "config": {
          "operation": "insert",
          "table": "test_users",
          "data": {
            "name": "прывет",
            "email": "workflow22@example.com",
            "status": "active"
          }
        },
        "position": {
          "x": 100,
          "y": 100
        }
      }
    ],
    "isActive": true,
    "id": "wf_1768167736541_y6olzzv48",
    "createdAt": "2026-01-11T21:42:16.541Z",
    "updatedAt": "2026-01-11T21:42:16.541Z"
  },
  {
    "name": "Workflow 1768167734871",
    "description": "",
    "trigger": {
      "id": "trigger_1",
      "type": "webhook",
      "config": {
        "url": "",
        "method": "POST",
        "headers": {}
      }
    },
    "actions": [
      {
        "id": "action_1",
        "type": "database",
        "config": {
          "operation": "insert",
          "table": "test_users",
          "data": {
            "name": "прывет",
            "email": "workflow22@example.com",
            "status": "active"
          }
        },
        "position": {
          "x": 100,
          "y": 100
        }
      }
    ],
    "isActive": true,
    "id": "wf_1768167736550_agtg8v2tl",
    "createdAt": "2026-01-11T21:42:16.550Z",
    "updatedAt": "2026-01-11T21:42:16.550Z"
  },
  {
    "name": "Workflow 1768167734956",
    "description": "",
    "trigger": {
      "id": "trigger_1",
      "type": "webhook",
      "config": {
        "url": "",
        "method": "POST",
        "headers": {}
      }
    },
    "actions": [
      {
        "id": "action_1",
        "type": "database",
        "config": {
          "operation": "insert",
          "table": "test_users",
          "data": {
            "name": "прывет",
            "email": "workflow22@example.com",
            "status": "active"
          }
        },
        "position": {
          "x": 100,
          "y": 100
        }
      }
    ],
    "isActive": true,
    "id": "wf_1768167736559_1ei8zqmly",
    "createdAt": "2026-01-11T21:42:16.559Z",
    "updatedAt": "2026-01-11T21:42:16.559Z"
  },
  {
    "name": "Workflow 1768167734983",
    "description": "",
    "trigger": {
      "id": "trigger_1",
      "type": "webhook",
      "config": {
        "url": "",
        "method": "POST",
        "headers": {}
      }
    },
    "actions": [
      {
        "id": "action_1",
        "type": "database",
        "config": {
          "operation": "insert",
          "table": "test_users",
          "data": {
            "name": "прывет",
            "email": "workflow22@example.com",
            "status": "active"
          }
        },
        "position": {
          "x": 100,
          "y": 100
        }
      }
    ],
    "isActive": true,
    "id": "wf_1768167736569_g6lz2tu2o",
    "createdAt": "2026-01-11T21:42:16.569Z",
    "updatedAt": "2026-01-11T21:42:16.569Z"
  }
]